[{"school_name":"Belmont Junior School","school_urn":"102078","address":"Rusper Road, London","postcode":"N22 6RA","latitude":51.59210649306818,"longitude":-0.09417100035821177,"phase":"primary","establishment_type":"Community school","is_open":true,"distance_km":1.175,"accessibility_band":"close","proximity_score":80.42,"ofsted_rating_latest":"Outstanding","ofsted_inspection_date_latest":"09/01/2008","ofsted_report_url":null,"data_quality_status":"complete","data_quality_flags":[]},{"school_name":"Belmont Infant School","school_urn":"102079","address":"Rusper Road, Belmont Infant School Rusper Road, London","postcode":"N22 6RA","latitude":51.59210649306818,"longitude":-0.09417100035821177,"phase":"primary","establishment_type":"Community school","is_open":true,"distance_km":1.175,"accessibility_band":"close","proximity_score":80.42,"ofsted_rating_latest":"Good","ofsted_inspection_date_latest":"23/05/2013","ofsted_report_url":null,"data_quality_status":"complete","data_quality_flags":[]},{"school_name":"Bounds Green Junior School","school_urn":"102080","address":"Bounds Green Road, London","postcode":"N11 2QG","latitude":51.60617477708721,"longitude":-0.12401020502289559,"phase":"primary","establishment_type":"Community school","is_open":true,"distance_km":1.951,"accessibility_band":"close","proximity_score":67.48,"ofsted_rating_latest":"Good","ofsted_inspection_date_latest":"12/02/2013","ofsted_report_url":null,"data_quality_status":"complete","data_quality_flags":[]},{"school_name":"Bounds Green Infant School","school_urn":"102081","address":"Bounds Green Road, London","postcode":"N11 2QG","latitude":51.60617477708721,"longitude":-0.12401020502289559,"phase":"primary","establishment_type":"Community school","is_open":true,"distance_km":1.951,"accessibility_band":"close","proximity_score":67.48,"ofsted_rating_latest":"Outstanding","ofsted_inspection_date_latest":"04/05/2017","ofsted_report_url":null,"data_quality_status":"complete","data_quality_flags":[]},{"school_name":"Campsbourne Junior School","school_urn":"102084","address":"Nightingale Lane, London","postcode":"N8 7AF","latitude":51.59047072280211,"longitude":-0.1221164218866161,"phase":"primary","establishment_type":"Community school","is_open":true,"distance_km":0.768,"accessibility_band":"very_close","proximity_score":87.2,"ofsted_rating_latest":"Good","ofsted_inspection_date_latest":"10/06/2013","ofsted_report_url":null,"data_quality_status":"complete","data_quality_flags":[]},{"school_name":"Campsbourne Infant School","school_urn":"102085","address":"Nightingale Lane, London","postcode":"N8 7AF","latitude":51.59047072280211,"longitude":-0.1221164218866161,"phase":"primary","establishment_type":"Community school","is_open":true,"distance_km":0.768,"accessibility_band":"very_close","proximity_score":87.2,"ofsted_rating_latest":"Good","ofsted_inspection_date_latest":"19/12/2017","ofsted_report_url":null,"data_quality_status":"complete","data_quality_flags":[]},{"school_name":"The Devonshire Hill Nursery & Primary School","school_urn":"102087","address":"Weir Hall Road, Tottenham, The Devonshire Hill Nursery & Primary School, London","postcode":"N17 8LB","latitude":51.60713395180879,"longitude":-0.08099175258369204,"phase":"primary","establishment_type":"Community school","is_open":true,"distance_km":2.771,"accessibility_band":"moderate","proximity_score":53.82,"ofsted_rating_latest":"Good","ofsted_inspection_date_latest":"08/02/2012","ofsted_report_url":null,"data_quality_status":"complete","data_quality_flags":[]},{"school_name":"Earlsmead Primary School","school_urn":"102091","address":"Broad Lane, Tottenham, London","postcode":"N15 4PW","latitude":51.58383647253853,"longitude":-0.0685061240387822,"phase":"primary","establishment_type":"Community school","is_open":true,"distance_km":3.031,"accessibility_band":"moderate","proximity_score":49.48,"ofsted_rating_latest":"Good","ofsted_inspection_date_latest":"04/07/2012","ofsted_report_url":null,"data_quality_status":"complete","data_quality_flags":[]},{"school_name":"Highgate Primary School","school_urn":"102092","address":"North Hill, Highgate, London","postcode":"N6 4ED","latitude":51.57921309975587,"longitude":-0.1550545798623459,"phase":"primary","establishment_type":"Community school","is_open":true,"distance_km":3.297,"accessibility_band":"moderate","proximity_score":45.05,"ofsted_rating_latest":"Good","ofsted_inspection_date_latest":"16/09/2013","ofsted_report_url":null,"data_quality_status":"complete","data_quality_flags":[]},{"school_name":"Lancasterian Primary School","school_urn":"102094","address":"King's Road, Tottenham, London","postcode":"N17 8NN","latitude":51.60157003820788,"longitude":-0.07181137726939009,"phase":"primary","establishment_type":"Community school","is_open":true,"distance_km":2.969,"accessibility_band":"moderate","proximity_score":50.52,"ofsted_rating_latest":"Good","ofsted_inspection_date_latest":"28/06/2013","ofsted_report_url":null,"data_quality_status":"complete","data_quality_flags":[]},{"school_name":"Coldfall Primary School","school_urn":"102097","address":"Coldfall Avenue, Muswell Hill, London","postcode":"N10 1HS","latitude":51.59674902605567,"longitude":-0.15453173080954186,"phase":"primary","establishment_type":"Community school","is_open":true,"distance_km":3.084,"accessibility_band":"moderate","proximity_score":48.6,"ofsted_rating_latest":"Outstanding","ofsted_inspection_date_latest":"14/01/2015","ofsted_report_url":null,"data_quality_status":"complete","data_quality_flags":[]},{"school_name":"Tetherdown Primary School","school_urn":"102098","address":"Grand Avenue, London","postcode":"N10 3BP","latitude":51.58796769186313,"longitude":-0.1519427262043848,"phase":"primary","establishment_type":"Community school","is_open":true,"distance_km":2.844,"accessibility_band":"moderate","proximity_score":52.6,"ofsted_rating_latest":"Good","ofsted_inspection_date_latest":"17/07/2013","ofsted_report_url":null,"data_quality_status":"complete","data_quality_flags":[]},{"school_name":"Rokesly Junior School","school_urn":"102106","address":"Rokesly Avenue, London","postcode":"N8 8NH","latitude":51.583121743761815,"longitude":-0.11973466638093175,"phase":"primary","establishment_type":"Community school","is_open":true,"distance_km":1.027,"accessibility_band":"close","proximity_score":82.88,"ofsted_rating_latest":"Good","ofsted_inspection_date_latest":"07/07/2015","ofsted_report_url":null,"data_quality_status":"complete","data_quality_flags":[]},{"school_name":"Rokesly Infant & Nursery School","school_urn":"102107","address":"Hermiston Avenue, Crouch End, London","postcode":"N8 8NH","latitude":51.583121743761815,"longitude":-0.11973466638093175,"phase":"primary","establishment_type":"Community school","is_open":true,"distance_km":1.027,"accessibility_band":"close","proximity_score":82.88,"ofsted_rating_latest":"Good","ofsted_inspection_date_latest":"02/07/2015","ofsted_report_url":null,"data_quality_status":"complete","data_quality_flags":[]},{"school_name":"South Harringay Junior School","school_urn":"102110","address":"Pemberton Rd, London","postcode":"N4 1BA","latitude":51.58045871211867,"longitude":-0.10122555580715978,"phase":"primary","establishment_type":"Community school","is_open":true,"distance_km":1.314,"accessibility_band":"close","proximity_score":78.1,"ofsted_rating_latest":"Good","ofsted_inspection_date_latest":"08/01/2013","ofsted_report_url":null,"data_quality_status":"complete","data_quality_flags":[]},{"school_name":"South Harringay Infant School","school_urn":"102111","address":"Pemberton Road, Haringey, London","postcode":"N4 1BA","latitude":51.580398841090386,"longitude":-0.10141568509673617,"phase":"primary","establishment_type":"Community school","is_open":true,"distance_km":1.313,"accessibility_band":"close","proximity_score":78.12,"ofsted_rating_latest":"Good","ofsted_inspection_date_latest":"17/07/2012","ofsted_report_url":null,"data_quality_status":"complete","data_quality_flags":[]},{"school_name":"West Green Primary School","school_urn":"102115","address":"Woodlands Park Road, Tottenham, London","postcode":"N15 3RT","latitude":51.58483240270198,"longitude":-0.09366705348973507,"phase":"primary","establishment_type":"Community school","is_open":true,"distance_km":1.358,"accessibility_band":"close","proximity_score":77.37,"ofsted_rating_latest":"Good","ofsted_inspection_date_latest":"05/10/2016","ofsted_report_url":null,"data_quality_status":"complete","data_quality_flags":[]},{"school_name":"Coleridge Primary School","school_urn":"102121","address":"Crouch End Hill, Hornsey, London","postcode":"N8 8DN","latitude":51.57572502651868,"longitude":-0.12729915623882793,"phase":"primary","establishment_type":"Community school","is_open":true,"distance_km":2.001,"accessibility_band":"moderate","proximity_score":66.65,"ofsted_rating_latest":"Outstanding","ofsted_inspection_date_latest":"20/04/2015","ofsted_report_url":null,"data_quality_status":"complete","data_quality_flags":[]},{"school_name":"Welbourne Primary School","school_urn":"102124","address":"Stainby Road, Tottenham, Stainby Road, London","postcode":"N15 4EA","latitude":51.588069852981725,"longitude":-0.06728719287655695,"phase":"primary","establishment_type":"Community school","is_open":true,"distance_km":3.033,"accessibility_band":"moderate","proximity_score":49.45,"ofsted_rating_latest":"Good","ofsted_inspection_date_latest":"03/12/2013","ofsted_report_url":null,"data_quality_status":"complete","data_quality_flags":[]},{"school_name":"Lea Valley Primary School","school_urn":"102125","address":"Somerford Grove, London","postcode":"N17 0PT","latitude":51.603788662180776,"longitude":-0.06074234254414824,"phase":"primary","establishment_type":"Community school","is_open":true,"distance_km":3.768,"accessibility_band":"moderate","proximity_score":37.2,"ofsted_rating_latest":"Good","ofsted_inspection_date_latest":"04/09/2013","ofsted_report_url":null,"data_quality_status":"complete","data_quality_flags":[]},{"school_name":"Ferry Lane Primary School","school_urn":"102127","address":"Jarrow Road, Ferry Lane Estate, Tottenham, London","postcode":"N17 9PP","latitude":51.585421830855594,"longitude":-0.05777140670174675,"phase":"primary","establishment_type":"Community school","is_open":true,"distance_km":3.722,"accessibility_band":"moderate","proximity_score":37.97,"ofsted_rating_latest":"Good","ofsted_inspection_date_latest":"05/06/2014","ofsted_report_url":null,"data_quality_status":"complete","data_quality_flags":[]},{"school_name":"Rhodes Avenue Primary School","school_urn":"102128","address":"Rhodes Avenue, London","postcode":"N22 7UT","latitude":51.601201609107285,"longitude":-0.13583929696090935,"phase":"primary","establishment_type":"Community school","is_open":true,"distance_km":2.082,"accessibility_band":"moderate","proximity_score":65.3,"ofsted_rating_latest":"Outstanding","ofsted_inspection_date_latest":"22/03/2007","ofsted_report_url":null,"data_quality_status":"complete","data_quality_flags":[]},{"school_name":"Crowland Primary School","school_urn":"102129","address":"Crowland Road, London","postcode":"N15 6UX","latitude":51.58062970130924,"longitude":-0.06708328541566286,"phase":"primary","establishment_type":"Community school","is_open":true,"distance_km":3.23,"accessibility_band":"moderate","proximity_score":46.17,"ofsted_rating_latest":"Outstanding","ofsted_inspection_date_latest":"01/09/2014","ofsted_report_url":null,"data_quality_status":"complete","data_quality_flags":[]},{"school_name":"Weston Park Primary School","school_urn":"102130","address":"Denton Road, Hornsey, London","postcode":"N8 9WP","latitude":51.58058930543564,"longitude":-0.11266580476167601,"phase":"primary","establishment_type":"Community school","is_open":true,"distance_km":1.119,"accessibility_band":"close","proximity_score":81.35,"ofsted_rating_latest":"Good","ofsted_inspection_date_latest":"13/12/2012","ofsted_report_url":null,"data_quality_status":"complete","data_quality_flags":[]},{"school_name":"The Willow Primary School","school_urn":"102131","address":"Adams Road, Tottenham, London","postcode":"N17 6HW","latitude":51.59611818495526,"longitude":-0.08209141215502908,"phase":"primary","establishment_type":"Community school","is_open":true,"distance_km":2.089,"accessibility_band":"moderate","proximity_score":65.18,"ofsted_rating_latest":"Outstanding","ofsted_inspection_date_latest":"22/06/2017","ofsted_report_url":null,"data_quality_status":"complete","data_quality_flags":[]},{"school_name":"St Aidan's Voluntary Controlled Primary School","school_urn":"102132","address":"Albany Road, Stroud Green, London","postcode":"N4 4RR","latitude":51.575204764445104,"longitude":-0.11055093013293273,"phase":"primary","establishment_type":"Voluntary controlled school","is_open":true,"distance_km":1.712,"accessibility_band":"close","proximity_score":71.47,"ofsted_rating_latest":"Outstanding","ofsted_inspection_date_latest":"20/04/2015","ofsted_report_url":null,"data_quality_status":"complete","data_quality_flags":[]},{"school_name":"St Michael's CofE Voluntary Aided Primary School","school_urn":"102135","address":"North Road, Highgate, London","postcode":"N6 4BG","latitude":51.57365755139143,"longitude":-0.15116666749922952,"phase":"primary","establishment_type":"Voluntary aided school","is_open":true,"distance_km":3.354,"accessibility_band":"moderate","proximity_score":44.1,"ofsted_rating_latest":"Good","ofsted_inspection_date_latest":"27/03/2015","ofsted_report_url":null,"data_quality_status":"complete","data_quality_flags":[]},{"school_name":"St James Church of England Primary School","school_urn":"102136","address":"Woodside Avenue, Muswell Hill, London","postcode":"N10 3JA","latitude":51.5863039457777,"longitude":-0.14907990491050435,"phase":"primary","establishment_type":"Voluntary aided school","is_open":true,"distance_km":2.674,"accessibility_band":"moderate","proximity_score":55.43,"ofsted_rating_latest":"Outstanding","ofsted_inspection_date_latest":"27/11/2007","ofsted_report_url":null,"data_quality_status":"complete","data_quality_flags":[]},{"school_name":"St Mary's CofE Primary School","school_urn":"102139","address":"Church Lane, Hornsey, London","postcode":"N8 7BU","latitude":51.58596301851918,"longitude":-0.11522909854971117,"phase":"primary","establishment_type":"Voluntary aided school","is_open":true,"distance_km":0.593,"accessibility_band":"very_close","proximity_score":90.12,"ofsted_rating_latest":"Good","ofsted_inspection_date_latest":"07/03/2014","ofsted_report_url":null,"data_quality_status":"complete","data_quality_flags":[]},{"school_name":"Our Lady of Muswell Catholic Primary School","school_urn":"102142","address":"Pages Lane, Muswell Hill, London","postcode":"N10 1PS","latitude":51.59426655399352,"longitude":-0.14878509999904738,"phase":"primary","establishment_type":"Voluntary aided school","is_open":true,"distance_km":2.642,"accessibility_band":"moderate","proximity_score":55.97,"ofsted_rating_latest":"Outstanding","ofsted_inspection_date_latest":"11/01/2018","ofsted_report_url":null,"data_quality_status":"complete","data_quality_flags":[]},{"school_name":"St Francis de Sales RC Junior School","school_urn":"102143","address":"Church Road, Tottenham, London","postcode":"N17 8AZ","latitude":51.602962518550505,"longitude":-0.06899423659334863,"phase":"primary","establishment_type":"Voluntary aided school","is_open":true,"distance_km":3.211,"accessibility_band":"moderate","proximity_score":46.48,"ofsted_rating_latest":"Good","ofsted_inspection_date_latest":"11/07/2016","ofsted_report_url":null,"data_quality_status":"complete","data_quality_flags":[]},{"school_name":"St Ignatius RC Primary School","school_urn":"102144","address":"St Ann's Road, Tottenham, London","postcode":"N15 6ND","latitude":51.57706980099368,"longitude":-0.07371446108381073,"phase":"primary","establishment_type":"Voluntary aided school","is_open":true,"distance_km":2.983,"accessibility_band":"moderate","proximity_score":50.28,"ofsted_rating_latest":"Good","ofsted_inspection_date_latest":"04/06/2015","ofsted_report_url":null,"data_quality_status":"complete","data_quality_flags":[]},{"school_name":"St Paul's Catholic Primary School","school_urn":"102146","address":"Bradley Road, Wood Green, London","postcode":"N22 7SZ","latitude":51.5973376020374,"longitude":-0.11517693956386629,"phase":"primary","establishment_type":"Voluntary aided school","is_open":true,"distance_km":0.803,"accessibility_band":"very_close","proximity_score":86.62,"ofsted_rating_latest":"Good","ofsted_inspection_date_latest":"08/11/2010","ofsted_report_url":null,"data_quality_status":"complete","data_quality_flags":[]},{"school_name":"St Francis de Sales RC Infant School","school_urn":"102149","address":"Church Road, Tottenham, London","postcode":"N17 8AZ","latitude":51.602628604839296,"longitude":-0.06892176026392129,"phase":"primary","establishment_type":"Voluntary aided school","is_open":true,"distance_km":3.199,"accessibility_band":"moderate","proximity_score":46.68,"ofsted_rating_latest":"Good","ofsted_inspection_date_latest":"03/02/2019","ofsted_report_url":null,"data_quality_status":"complete","data_quality_flags":[]},{"school_name":"St Martin of Porres Catholic Primary School","school_urn":"102150","address":"Blake Road, New Southgate, London","postcode":"N11 2AF","latitude":51.607914257346465,"longitude":-0.13328249644036502,"phase":"primary","establishment_type":"Voluntary aided school","is_open":true,"distance_km":2.465,"accessibility_band":"moderate","proximity_score":58.92,"ofsted_rating_latest":"Good","ofsted_inspection_date_latest":"18/10/2012","ofsted_report_url":null,"data_quality_status":"complete","data_quality_flags":[]},{"school_name":"St John Vianney RC Primary School","school_urn":"102152","address":"Stanley Road, Tottenham, London","postcode":"N15 3HD","latitude":51.58566923342714,"longitude":-0.09702426070285076,"phase":"primary","establishment_type":"Voluntary aided school","is_open":true,"distance_km":1.11,"accessibility_band":"close","proximity_score":81.5,"ofsted_rating_latest":"Good","ofsted_inspection_date_latest":"26/04/2017","ofsted_report_url":null,"data_quality_status":"complete","data_quality_flags":[]},{"school_name":"Hornsey School for Girls","school_urn":"102153","address":"Inderwick Road, London","postcode":"N8 9JF","latitude":51.58186653113332,"longitude":-0.11492229233473443,"phase":"secondary","establishment_type":"Community school","is_open":true,"distance_km":1.008,"accessibility_band":"very_close","proximity_score":89.92,"ofsted_rating_latest":"Good","ofsted_inspection_date_latest":"11/03/2013","ofsted_report_url":null,"data_quality_status":"complete","data_quality_flags":[]},{"school_name":"Highgate Wood Secondary School","school_urn":"102154","address":"Montenotte Road, London","postcode":"N8 8RN","latitude":51.58143814155262,"longitude":-0.13312641357903304,"phase":"secondary","establishment_type":"Community school","is_open":true,"distance_km":1.837,"accessibility_band":"very_close","proximity_score":81.63,"ofsted_rating_latest":"Good","ofsted_inspection_date_latest":"16/12/2011","ofsted_report_url":null,"data_quality_status":"complete","data_quality_flags":[]},{"school_name":"Fortismere School","school_urn":"102156","address":"Southwing, Tetherdown, Muswell Hill, London","postcode":"N10 1NE","latitude":51.59285336792349,"longitude":-0.1509792642123674,"phase":"secondary","establishment_type":"Foundation school","is_open":true,"distance_km":2.773,"accessibility_band":"close","proximity_score":72.27,"ofsted_rating_latest":"Outstanding","ofsted_inspection_date_latest":"09/12/2011","ofsted_report_url":null,"data_quality_status":"complete","data_quality_flags":[]},{"school_name":"Gladesmore Community School","school_urn":"102157","address":"Crowland Road, Tottenham, London","postcode":"N15 6EB","latitude":51.58006466998407,"longitude":-0.0660824959222623,"phase":"secondary","establishment_type":"Community school","is_open":true,"distance_km":3.317,"accessibility_band":"close","proximity_score":66.83,"ofsted_rating_latest":"Outstanding","ofsted_inspection_date_latest":"30/01/2014","ofsted_report_url":null,"data_quality_status":"complete","data_quality_flags":[]},{"school_name":"Alexandra Primary School","school_urn":"130358","address":"Western Road, London","postcode":"N22 6UH","latitude":51.595244918376935,"longitude":-0.1153357660678572,"phase":"primary","establishment_type":"Community school","is_open":true,"distance_km":0.597,"accessibility_band":"very_close","proximity_score":90.05,"ofsted_rating_latest":"Good","ofsted_inspection_date_latest":"04/03/2013","ofsted_report_url":null,"data_quality_status":"complete","data_quality_flags":[]},{"school_name":"Stroud Green Primary School","school_urn":"131096","address":"Woodstock Road, London","postcode":"N4 3EX","latitude":51.56907065725378,"longitude":-0.10712568418069153,"phase":"primary","establishment_type":"Community school","is_open":true,"distance_km":2.409,"accessibility_band":"moderate","proximity_score":59.85,"ofsted_rating_latest":"Good","ofsted_inspection_date_latest":"04/03/2013","ofsted_report_url":null,"data_quality_status":"complete","data_quality_flags":[]},{"school_name":"Earlham Primary School","school_urn":"131478","address":"Earlham Grove, Wood Green, London, Middlesex","postcode":"N22 5HJ","latitude":51.60313404586297,"longitude":-0.10879967987888073,"phase":"primary","establishment_type":"Community school","is_open":true,"distance_km":1.402,"accessibility_band":"close","proximity_score":76.63,"ofsted_rating_latest":"Good","ofsted_inspection_date_latest":"17/07/2017","ofsted_report_url":null,"data_quality_status":"complete","data_quality_flags":[]},{"school_name":"Lordship Lane Primary School","school_urn":"131595","address":"Ellenborough Road, Wood Green","postcode":"N22 5PS","latitude":51.59861524412553,"longitude":-0.09516916339771496,"phase":"primary","establishment_type":"Community school","is_open":true,"distance_km":1.411,"accessibility_band":"close","proximity_score":76.48,"ofsted_rating_latest":"Good","ofsted_inspection_date_latest":"02/09/2013","ofsted_report_url":null,"data_quality_status":"complete","data_quality_flags":[]},{"school_name":"Bruce Grove Primary School","school_urn":"131731","address":"Sperling Road, Tottenham, London","postcode":"N17 6UH","latitude":51.59345595630495,"longitude":-0.07218390025272992,"phase":"primary","establishment_type":"Community school","is_open":true,"distance_km":2.7,"accessibility_band":"moderate","proximity_score":55.0,"ofsted_rating_latest":"Good","ofsted_inspection_date_latest":"10/01/2013","ofsted_report_url":null,"data_quality_status":"complete","data_quality_flags":[]},{"school_name":"Park View School","school_urn":"131757","address":"252 West Green Road, Tottenham, Haringey, London","postcode":"N15 3QR","latitude":51.58719196329529,"longitude":-0.09056569424574,"phase":"secondary","establishment_type":"Community school","is_open":true,"distance_km":1.462,"accessibility_band":"very_close","proximity_score":85.38,"ofsted_rating_latest":"Good","ofsted_inspection_date_latest":"13/04/2013","ofsted_report_url":null,"data_quality_status":"complete","data_quality_flags":[]},{"school_name":"Muswell Hill Primary School","school_urn":"131871","address":"Muswell Hill, London","postcode":"N10 3ST","latitude":51.591440940627955,"longitude":-0.1395593800921588,"phase":"primary","establishment_type":"Community school","is_open":true,"distance_km":1.975,"accessibility_band":"close","proximity_score":67.08,"ofsted_rating_latest":"Outstanding","ofsted_inspection_date_latest":"22/12/2006","ofsted_report_url":null,"data_quality_status":"complete","data_quality_flags":[]},{"school_name":"Risley Avenue Primary School","school_urn":"131879","address":"The Roundway, Tottenham, London","postcode":"N17 7AB","latitude":51.60001030027727,"longitude":-0.07814424733569209,"phase":"primary","establishment_type":"Community school","is_open":true,"distance_km":2.499,"accessibility_band":"moderate","proximity_score":58.35,"ofsted_rating_latest":"Good","ofsted_inspection_date_latest":"01/03/2013","ofsted_report_url":null,"data_quality_status":"complete","data_quality_flags":[]},{"school_name":"South Grove Primary School","school_urn":"132253","address":"South Grove, Tottenham, London","postcode":"N15 5QE","latitude":51.58261418332729,"longitude":-0.08225592716629775,"phase":"primary","establishment_type":"Community school","is_open":true,"distance_km":2.175,"accessibility_band":"moderate","proximity_score":63.75,"ofsted_rating_latest":"Good","ofsted_inspection_date_latest":"08/03/2016","ofsted_report_url":null,"data_quality_status":"complete","data_quality_flags":[]},{"school_name":"Greig City Academy","school_urn":"133386","address":"High Street, Hornsey, Haringey, London","postcode":"N8 7NU","latitude":51.587387451626824,"longitude":-0.1176963678445283,"phase":"secondary","establishment_type":"Academy sponsor led","is_open":true,"distance_km":0.584,"accessibility_band":"very_close","proximity_score":94.16,"ofsted_rating_latest":"Good","ofsted_inspection_date_latest":"12/01/2020","ofsted_report_url":null,"data_quality_status":"complete","data_quality_flags":[]},{"school_name":"The Mulberry Primary School","school_urn":"133707","address":"Parkhurst Road, Tottenham, London","postcode":"N17 9RB","latitude":51.596253859945804,"longitude":-0.06624672837548051,"phase":"primary","establishment_type":"Community school","is_open":true,"distance_km":3.155,"accessibility_band":"moderate","proximity_score":47.42,"ofsted_rating_latest":"Good","ofsted_inspection_date_latest":"22/04/2013","ofsted_report_url":null,"data_quality_status":"complete","data_quality_flags":[]},{"school_name":"Chestnuts Primary School","school_urn":"134680","address":"Black Boy Lane, Tottenham, London","postcode":"N15 3AS","latitude":51.58308889112484,"longitude":-0.0915171554938209,"phase":"primary","establishment_type":"Foundation school","is_open":true,"distance_km":1.584,"accessibility_band":"close","proximity_score":73.6,"ofsted_rating_latest":"Good","ofsted_inspection_date_latest":"29/02/2016","ofsted_report_url":null,"data_quality_status":"complete","data_quality_flags":[]},{"school_name":"North Harringay Primary School","school_urn":"134681","address":"Falkland Road, Hornsey, London","postcode":"N8 0NU","latitude":51.585807864184034,"longitude":-0.10559290184628879,"phase":"primary","establishment_type":"Foundation school","is_open":true,"distance_km":0.651,"accessibility_band":"very_close","proximity_score":89.15,"ofsted_rating_latest":"Good","ofsted_inspection_date_latest":"13/02/2013","ofsted_report_url":null,"data_quality_status":"complete","data_quality_flags":[]},{"school_name":"Eden Primary","school_urn":"136808","address":"79 Creighton Avenue, Muswell Hill, London","postcode":"N10 1NR","latitude":51.595156878843135,"longitude":-0.15221400684898487,"phase":"primary","establishment_type":"Free schools","is_open":true,"distance_km":2.892,"accessibility_band":"moderate","proximity_score":51.8,"ofsted_rating_latest":"Good","ofsted_inspection_date_latest":"23/07/2013","ofsted_report_url":null,"data_quality_status":"complete","data_quality_flags":[]},{"school_name":"Alexandra Park School","school_urn":"137531","address":"Bidwell Gardens, London","postcode":"N11 2AZ","latitude":51.6020646743742,"longitude":-0.13695916373250355,"phase":"secondary","establishment_type":"Academy converter","is_open":true,"distance_km":2.2,"accessibility_band":"close","proximity_score":78.0,"ofsted_rating_latest":"Outstanding","ofsted_inspection_date_latest":"07/12/2011","ofsted_report_url":null,"data_quality_status":"complete","data_quality_flags":[]},{"school_name":"Mulberry Academy Woodside","school_urn":"137745","address":"White Hart Lane, Wood Green, London","postcode":"N22 5QJ","latitude":51.603502009624094,"longitude":-0.10095754118474784,"phase":"secondary","establishment_type":"Academy converter","is_open":true,"distance_km":1.594,"accessibility_band":"very_close","proximity_score":84.06,"ofsted_rating_latest":"Outstanding","ofsted_inspection_date_latest":"10/03/2014","ofsted_report_url":null,"data_quality_status":"complete","data_quality_flags":[]},{"school_name":"Harris Primary Academy Coleraine Park","school_urn":"138446","address":"Glendish Road, Tottenham, London","postcode":"N17 9XT","latitude":51.598112443434125,"longitude":-0.058991569786562545,"phase":"primary","establishment_type":"Academy sponsor led","is_open":true,"distance_km":3.688,"accessibility_band":"moderate","proximity_score":38.53,"ofsted_rating_latest":"Outstanding","ofsted_inspection_date_latest":"03/09/2014","ofsted_report_url":null,"data_quality_status":"complete","data_quality_flags":[]},{"school_name":"Harris Primary Academy Philip Lane","school_urn":"138447","address":"Philip Lane, Tottenham, London","postcode":"N15 4AB","latitude":51.58743589221968,"longitude":-0.08732188933548381,"phase":"primary","establishment_type":"Academy sponsor led","is_open":true,"distance_km":1.673,"accessibility_band":"close","proximity_score":72.12,"ofsted_rating_latest":"Outstanding","ofsted_inspection_date_latest":"24/04/2019","ofsted_report_url":null,"data_quality_status":"complete","data_quality_flags":[]},{"school_name":"Lift Noel Park","school_urn":"138588","address":"Gladstone Avenue, Wood Green, London","postcode":"N22 6LH","latitude":51.595348088382636,"longitude":-0.10331900870516322,"phase":"primary","establishment_type":"Academy sponsor led","is_open":true,"distance_km":0.749,"accessibility_band":"very_close","proximity_score":87.52,"ofsted_rating_latest":"Outstanding","ofsted_inspection_date_latest":"23/04/2019","ofsted_report_url":null,"data_quality_status":"complete","data_quality_flags":[]},{"school_name":"Lift Trinity","school_urn":"138589","address":"Bounds Green Road, Wood Green, London","postcode":"N22 8ES","latitude":51.60037694033803,"longitude":-0.11349160889378265,"phase":"primary","establishment_type":"Academy sponsor led","is_open":true,"distance_km":1.101,"accessibility_band":"close","proximity_score":81.65,"ofsted_rating_latest":"Outstanding","ofsted_inspection_date_latest":"07/07/2016","ofsted_report_url":null,"data_quality_status":"complete","data_quality_flags":[]},{"school_name":"St Ann's CE Primary School","school_urn":"139169","address":"Avenue Road, London","postcode":"N15 5JG","latitude":51.581803547280714,"longitude":-0.08547993501995947,"phase":"primary","establishment_type":"Academy converter","is_open":true,"distance_km":2.016,"accessibility_band":"moderate","proximity_score":66.4,"ofsted_rating_latest":"Requires improvement","ofsted_inspection_date_latest":"22/01/2020","ofsted_report_url":null,"data_quality_status":"complete","data_quality_flags":[]},{"school_name":"St Michael's CofE Primary School","school_urn":"139175","address":"Bounds Green Road, Wood Green, London","postcode":"N22 8HE","latitude":51.599371851410496,"longitude":-0.11361989841638506,"phase":"primary","establishment_type":"Academy converter","is_open":true,"distance_km":0.992,"accessibility_band":"very_close","proximity_score":83.47,"ofsted_rating_latest":"Good","ofsted_inspection_date_latest":"12/11/2012","ofsted_report_url":null,"data_quality_status":"complete","data_quality_flags":[]},{"school_name":"St Paul's and All Hallows CofE Infant School","school_urn":"139176","address":"Park Lane, London","postcode":"N17 0HH","latitude":51.602713755958746,"longitude":-0.06371956571020099,"phase":"primary","establishment_type":"Academy converter","is_open":true,"distance_km":3.533,"accessibility_band":"moderate","proximity_score":41.12,"ofsted_rating_latest":"Good","ofsted_inspection_date_latest":"05/09/2013","ofsted_report_url":null,"data_quality_status":"complete","data_quality_flags":[]},{"school_name":"St Paul's and All Hallows CofE Junior School","school_urn":"139177","address":"Worcester Avenue, London","postcode":"N17 0TU","latitude":51.60285658237693,"longitude":-0.06365572738729079,"phase":"primary","establishment_type":"Academy converter","is_open":true,"distance_km":3.543,"accessibility_band":"moderate","proximity_score":40.95,"ofsted_rating_latest":"Good","ofsted_inspection_date_latest":"16/09/2013","ofsted_report_url":null,"data_quality_status":"complete","data_quality_flags":[]},{"school_name":"Holy Trinity CofE Primary School","school_urn":"139240","address":"Somerset Road, Tottenham, London","postcode":"N17 9EJ","latitude":51.58969813297198,"longitude":-0.06896488490911025,"phase":"primary","establishment_type":"Academy sponsor led","is_open":true,"distance_km":2.906,"accessibility_band":"moderate","proximity_score":51.57,"ofsted_rating_latest":"Good","ofsted_inspection_date_latest":"27/02/2015","ofsted_report_url":null,"data_quality_status":"complete","data_quality_flags":[]},{"school_name":"St Thomas More Catholic School","school_urn":"139362","address":"Glendale Avenue, Wood Green, London","postcode":"N22 5HN","latitude":51.60447371734656,"longitude":-0.10878733598318391,"phase":"secondary","establishment_type":"Academy converter","is_open":true,"distance_km":1.55,"accessibility_band":"very_close","proximity_score":84.5,"ofsted_rating_latest":"Outstanding","ofsted_inspection_date_latest":"10/07/2013","ofsted_report_url":null,"data_quality_status":"complete","data_quality_flags":[]},{"school_name":"Heartlands High School","school_urn":"139616","address":"Station Road, Wood Green, London","postcode":"N22 7ST","latitude":51.597739999178486,"longitude":-0.11952080554888604,"phase":"secondary","establishment_type":"Academy converter","is_open":true,"distance_km":0.988,"accessibility_band":"very_close","proximity_score":90.12,"ofsted_rating_latest":"Good","ofsted_inspection_date_latest":"28/04/2016","ofsted_report_url":null,"data_quality_status":"complete","data_quality_flags":[]},{"school_name":"Harris Academy Tottenham","school_urn":"140935","address":"Ashley Road, Tottenham, London","postcode":"N17 9LN","latitude":51.59131667929891,"longitude":-0.0602341100041394,"phase":"all_through","establishment_type":"Free schools","is_open":true,"distance_km":3.508,"accessibility_band":"close","proximity_score":64.92,"ofsted_rating_latest":"Outstanding","ofsted_inspection_date_latest":"18/07/2017","ofsted_report_url":null,"data_quality_status":"complete","data_quality_flags":[]},{"school_name":"Brook House Primary School","school_urn":"141209","address":"881 High Road, Tottenham, London","postcode":"N17 8EY","latitude":51.608316150727745,"longitude":-0.06863708728230339,"phase":"primary","establishment_type":"Free schools","is_open":true,"distance_km":3.527,"accessibility_band":"moderate","proximity_score":41.22,"ofsted_rating_latest":"Good","ofsted_inspection_date_latest":"18/01/2017","ofsted_report_url":null,"data_quality_status":"complete","data_quality_flags":[]},{"school_name":"Duke's Aldridge","school_urn":"144900","address":"Trulock Road, Tottenham, London","postcode":"N17 0PG","latitude":51.604910604565944,"longitude":-0.06333727796986745,"phase":"secondary","establishment_type":"Academy converter","is_open":true,"distance_km":3.657,"accessibility_band":"close","proximity_score":63.43,"ofsted_rating_latest":"Good","ofsted_inspection_date_latest":"09/02/2012","ofsted_report_url":null,"data_quality_status":"complete","data_quality_flags":[]},{"school_name":"St Mary's Priory Catholic Junior School","school_urn":"152286","address":"Hermitage Road, LONDON","postcode":"N15 5RE","latitude":51.579953966655125,"longitude":-0.08620716767039538,"phase":"primary","establishment_type":"Academy converter","is_open":true,"distance_km":2.082,"accessibility_band":"moderate","proximity_score":65.3,"ofsted_rating_latest":null,"ofsted_inspection_date_latest":null,"ofsted_report_url":null,"data_quality_status":"partial","data_quality_flags":["missing_ofsted_rating","missing_inspection_date"]},{"school_name":"St Mary's Priory Catholic Infant School","school_urn":"152287","address":"Hermitage Road, Tottenham, London","postcode":"N15 5RE","latitude":51.579953966655125,"longitude":-0.08620716767039538,"phase":"primary","establishment_type":"Academy converter","is_open":true,"distance_km":2.082,"accessibility_band":"moderate","proximity_score":65.3,"ofsted_rating_latest":null,"ofsted_inspection_date_latest":null,"ofsted_report_url":null,"data_quality_status":"partial","data_quality_flags":["missing_ofsted_rating","missing_inspection_date"]}]